pcodegenerator/__init__.py
pcodegenerator/__version__.py
pcodegenerator/generator.py
pcodegenerator/prepare.py
pcodegenerator-0.2.2.dist-info/entry_points.txt
pcodegenerator-0.2.2.dist-info/WHEEL
pcodegenerator-0.2.2.dist-info/METADATA
pcodegenerator-0.2.2.dist-info/licenses/LICENSE
pcodegenerator-0.2.2.dist-info/RECORD
