Metadata-Version: 2.1
Name: pcodegenerator
Version: 0.2.2
Summary: Command line script to generate pcodes from your spatial dataset
License: GPL-3.0-only
Keywords: pcode,humanitarian,duckdb
Author-email: Kshitij Raj Sharma <skshitizraj@gmail.com>
Requires-Python: >=3.9
Classifier: Programming Language :: Python :: 3
Classifier: Programming Language :: Python :: 3.10
Classifier: Programming Language :: Python :: 3.11
Classifier: Programming Language :: Python :: 3.9
Classifier: Topic :: Scientific/Engineering :: GIS
Classifier: Topic :: Utilities
Requires-Dist: duckdb>=1.1.0
Requires-Dist: geopandas>=1.0.1
Requires-Dist: requests>=2.32.3
Provides-Extra: docs
Requires-Dist: mkdocs>=1.5.3; extra == "docs"
Requires-Dist: mkdocs-material>=9.4.2; extra == "docs"
Requires-Dist: mkdocstrings-python>=1.7.0; extra == "docs"
Requires-Dist: mkdocs-exclude>=1.0.2; extra == "docs"
Provides-Extra: test
Requires-Dist: pytest>=7.4.2; extra == "test"
Requires-Dist: pytest-mock>=3.14.0; extra == "test"
Requires-Dist: coverage>=7.6.1; extra == "test"
Requires-Dist: coverage-badge>=1.1.2; extra == "test"
Project-URL: documentation, https://github.com/kshitijrajsharma/pcodegenerator
Project-URL: homepage, https://github.com/kshitijrajsharma/pcodegenerator
Project-URL: repository, https://github.com/kshitijrajsharma/pcodegenerator
